<?xml version="1.0" encoding="utf-8"?>
<!-- Created by ModBuddy on 1/7/2014 10:51:42 PM -->
<GameData>
	<IconTextureAtlases>

		<Row>
			<Atlas>CIV_COLOR_ATLAS_NOTI_MISHKEH</Atlas>
			<IconSize>80</IconSize>
			<Filename>MishkehNotification80.dds</Filename>
			<IconsPerRow>1</IconsPerRow>
			<IconsPerColumn>1</IconsPerColumn>
		</Row>
		
		<Row>
			<Atlas>CIV_COLOR_ATLAS_LEUGI_PHILISTINE</Atlas>
			<IconSize>256</IconSize>
			<Filename>PhilistiaIcons256.dds</Filename>
			<IconsPerRow>3</IconsPerRow>
			<IconsPerColumn>2</IconsPerColumn>
		</Row>
		<Row>
			<Atlas>CIV_COLOR_ATLAS_LEUGI_PHILISTINE</Atlas>
			<IconSize>128</IconSize>
			<Filename>PhilistiaIcons128.dds</Filename>
			<IconsPerRow>3</IconsPerRow>
			<IconsPerColumn>2</IconsPerColumn>
		</Row>
		<Row>
			<Atlas>CIV_COLOR_ATLAS_LEUGI_PHILISTINE</Atlas>
			<IconSize>80</IconSize>
			<Filename>PhilistiaIcons80.dds</Filename>
			<IconsPerRow>3</IconsPerRow>
			<IconsPerColumn>2</IconsPerColumn>
		</Row>
		<Row>
			<Atlas>CIV_COLOR_ATLAS_LEUGI_PHILISTINE</Atlas>
			<IconSize>64</IconSize>
			<Filename>PhilistiaIcons64.dds</Filename>
			<IconsPerRow>3</IconsPerRow>
			<IconsPerColumn>2</IconsPerColumn>
		</Row>
		<Row>
			<Atlas>CIV_COLOR_ATLAS_LEUGI_PHILISTINE</Atlas>
			<IconSize>48</IconSize>
			<Filename>PhilistiaIcons48.dds</Filename>
			<IconsPerRow>3</IconsPerRow>
			<IconsPerColumn>2</IconsPerColumn>
		</Row>
		<Row>
			<Atlas>CIV_COLOR_ATLAS_LEUGI_PHILISTINE</Atlas>
			<IconSize>45</IconSize>
			<Filename>PhilistiaIcons45.dds</Filename>
			<IconsPerRow>3</IconsPerRow>
			<IconsPerColumn>2</IconsPerColumn>
		</Row>
		<Row>
			<Atlas>CIV_COLOR_ATLAS_LEUGI_PHILISTINE</Atlas>
			<IconSize>32</IconSize>
			<Filename>PhilistiaIcons32.dds</Filename>
			<IconsPerRow>3</IconsPerRow>
			<IconsPerColumn>2</IconsPerColumn>
		</Row>
		<Row>
			<Atlas>CIV_COLOR_ATLAS_LEUGI_PHILISTINE</Atlas>
			<IconSize>24</IconSize>
			<Filename>PhilistiaIcons24.dds</Filename>
			<IconsPerRow>3</IconsPerRow>
			<IconsPerColumn>2</IconsPerColumn>
		</Row>
		<Row>
			<Atlas>CIV_COLOR_ATLAS_LEUGI_PHILISTINE</Atlas>
			<IconSize>16</IconSize>
			<Filename>PhilistiaIcons16.dds</Filename>
			<IconsPerRow>3</IconsPerRow>
			<IconsPerColumn>2</IconsPerColumn>
		</Row>


		<Row>
			<Atlas>CIV_COLOR_ATLAS_LEUGI_PHILISTINE_ALPHA</Atlas>
			<IconSize>256</IconSize>
			<Filename>PhilistiaIcons256.dds</Filename>
			<IconsPerRow>1</IconsPerRow>
			<IconsPerColumn>2</IconsPerColumn>
		</Row>
		<Row>
			<Atlas>CIV_COLOR_ATLAS_LEUGI_PHILISTINE_ALPHA</Atlas>
			<IconSize>128</IconSize>
			<Filename>PhilistiaIcons128.dds</Filename>
			<IconsPerRow>1</IconsPerRow>
			<IconsPerColumn>2</IconsPerColumn>
		</Row>
		<Row>
			<Atlas>CIV_COLOR_ATLAS_LEUGI_PHILISTINE_ALPHA</Atlas>
			<IconSize>80</IconSize>
			<Filename>PhilistiaIcons80.dds</Filename>
			<IconsPerRow>1</IconsPerRow>
			<IconsPerColumn>2</IconsPerColumn>
		</Row>
		<Row>
			<Atlas>CIV_COLOR_ATLAS_LEUGI_PHILISTINE_ALPHA</Atlas>
			<IconSize>64</IconSize>
			<Filename>PhilistiaIcons64.dds</Filename>
			<IconsPerRow>1</IconsPerRow>
			<IconsPerColumn>2</IconsPerColumn>
		</Row>
		<Row>
			<Atlas>CIV_COLOR_ATLAS_LEUGI_PHILISTINE_ALPHA</Atlas>
			<IconSize>48</IconSize>
			<Filename>PhilistiaIcons48.dds</Filename>
			<IconsPerRow>1</IconsPerRow>
			<IconsPerColumn>2</IconsPerColumn>
		</Row>
		<Row>
			<Atlas>CIV_COLOR_ATLAS_LEUGI_PHILISTINE_ALPHA</Atlas>
			<IconSize>45</IconSize>
			<Filename>PhilistiaIcons45.dds</Filename>
			<IconsPerRow>1</IconsPerRow>
			<IconsPerColumn>2</IconsPerColumn>
		</Row>
		<Row>
			<Atlas>CIV_COLOR_ATLAS_LEUGI_PHILISTINE_ALPHA</Atlas>
			<IconSize>32</IconSize>
			<Filename>PhilistiaIcons32.dds</Filename>
			<IconsPerRow>1</IconsPerRow>
			<IconsPerColumn>2</IconsPerColumn>
		</Row>
		<Row>
			<Atlas>CIV_COLOR_ATLAS_LEUGI_PHILISTINE_ALPHA</Atlas>
			<IconSize>24</IconSize>
			<Filename>PhilistiaIcons24.dds</Filename>
			<IconsPerRow>1</IconsPerRow>
			<IconsPerColumn>2</IconsPerColumn>
		</Row>
		<Row>
			<Atlas>CIV_COLOR_ATLAS_LEUGI_PHILISTINE_ALPHA</Atlas>
			<IconSize>16</IconSize>
			<Filename>PhilistiaIcons16.dds</Filename>
			<IconsPerRow>1</IconsPerRow>
			<IconsPerColumn>2</IconsPerColumn>
		</Row>


		<Row>
			<Atlas>PELESET_FLAG</Atlas>
			<IconSize>32</IconSize>
			<Filename>flag_peleset.dds</Filename>
			<IconsPerRow>1</IconsPerRow>
			<IconsPerColumn>1</IconsPerColumn>
		</Row>


	</IconTextureAtlases>
	<ArtDefine_StrategicView>
		<Replace>
			<StrategicViewType>ART_DEF_UNIT_LEUGI_PELESET</StrategicViewType>
			<TileType>Unit</TileType>
			<Asset>sv_peleset.dds</Asset>
		</Replace>
	</ArtDefine_StrategicView>
</GameData>