<?xml version="1.0" encoding="utf-8"?>

<GameData>
	<Audio_Sounds>
		<Row>
			<SoundID>SND_LEADER_MUSIC_TCM_PTOLEMY_PEACE</SoundID>
			<Filename>ptolemypeace</Filename>
			<LoadType>DynamicResident</LoadType>
		</Row>
		<Row>
			<SoundID>SND_LEADER_MUSIC_TCM_PTOLEMY_WAR</SoundID>
			<Filename>ptolemywar</Filename>
			<LoadType>DynamicResident</LoadType>
		</Row>
	</Audio_Sounds>
	<Audio_2DSounds>
		<Row>
			<ScriptID>AS2D_LEADER_MUSIC_TCM_PTOLEMY_PEACE</ScriptID>
			<SoundID>SND_LEADER_MUSIC_TCM_PTOLEMY_PEACE</SoundID>
			<SoundType>GAME_MUSIC</SoundType>
			<MinVolume>80</MinVolume>
			<MaxVolume>80</MaxVolume>
			<IsMusic>true</IsMusic>
		</Row>
		<Row>
			<ScriptID>AS2D_LEADER_MUSIC_TCM_PTOLEMY_WAR</ScriptID>
			<SoundID>SND_LEADER_MUSIC_TCM_PTOLEMY_WAR</SoundID>
			<SoundType>GAME_MUSIC</SoundType>
			<MinVolume>80</MinVolume>
			<MaxVolume>80</MaxVolume>
			<IsMusic>true</IsMusic>
		</Row>
	</Audio_2DSounds>
</GameData>
